common_python_tasks/__init__.py
common_python_tasks/data/.coveragerc
common_python_tasks/data/.dockerignore
common_python_tasks/data/.flake8
common_python_tasks/data/.isort.cfg
common_python_tasks/data/Containerfile
common_python_tasks/data/pytest.ini
common_python_tasks/tasks.py
common_python_tasks-0.0.2.dist-info/METADATA
common_python_tasks-0.0.2.dist-info/WHEEL
common_python_tasks-0.0.2.dist-info/licenses/LICENSE
common_python_tasks-0.0.2.dist-info/RECORD
