Metadata-Version: 2.4
Name: common-python-tasks
Version: 0.0.2
Summary: Opinionated Poe the Poet tasks for Python package development.
License-Expression: MIT
License-File: LICENSE
Author: Joseph Asbury
Author-email: ci_sourcerer@yahoo.com
Requires-Python: >=3.10,<4.0
Classifier: Development Status :: 3 - Alpha
Classifier: Intended Audience :: Developers
Classifier: Programming Language :: Python :: 3
Classifier: Programming Language :: Python :: 3.10
Classifier: Programming Language :: Python :: 3.11
Classifier: Programming Language :: Python :: 3.12
Classifier: Programming Language :: Python :: 3.13
Classifier: Programming Language :: Python :: 3.14
Classifier: Topic :: Software Development :: Build Tools
Requires-Dist: autoflake (>=2.3.1,<3.0.0)
Requires-Dist: black (>=25.11.0,<26.0.0)
Requires-Dist: dunamai (>=1.25.0,<2.0.0)
Requires-Dist: flake8 (>=7.3.0,<8.0.0)
Requires-Dist: isort (>=7.0.0,<8.0.0)
Requires-Dist: poethepoet-tasks (>=0.3.0,<0.4.0)
Requires-Dist: pytest (>=9.0.1,<10.0.0)
Requires-Dist: pytest-cov (>=7.0.0,<8.0.0)
Requires-Dist: tomlkit (>=0.13.3,<0.14.0)
Project-URL: Homepage, http://github.com/ci-sourcerer/common-python-tasks
Project-URL: Issues, http://github.com/ci-sourcerer/common-python-tasks/issues
Project-URL: Source, http://github.com/ci-sourcerer/common-python-tasks.git
